{
  "generated_at": "2026-06-23T11:40:22.320024Z",
  "merge_strategy": "url_or_title_similarity_v0_6",
  "total_events": 18,
  "events": [
    {
      "story_id": "story_774f7412d1a3",
      "item_id": "70cc18365043149c21091449fb5fa437500f3cae",
      "merged_into": "story_774f7412d1a3",
      "reason": "canonical_url",
      "similarity": 1.0
    },
    {
      "story_id": "story_774f7412d1a3",
      "item_id": "2e6e8c4a284999b403779b442ca22b227ba939c0",
      "merged_into": "story_774f7412d1a3",
      "reason": "canonical_url",
      "similarity": 1.0
    },
    {
      "story_id": "story_774f7412d1a3",
      "item_id": "4b18a63de7685ed4dd561f31a3eceecb6edf7658",
      "merged_into": "story_774f7412d1a3",
      "reason": "canonical_url",
      "similarity": 1.0
    },
    {
      "story_id": "story_774f7412d1a3",
      "item_id": "a5da70c440db72df9600615776089369eb57e0f0",
      "merged_into": "story_774f7412d1a3",
      "reason": "canonical_url",
      "similarity": 1.0
    },
    {
      "story_id": "story_774f7412d1a3",
      "item_id": "04c44074a5cdedebc76b6bbc391275d688184c8f",
      "merged_into": "story_774f7412d1a3",
      "reason": "canonical_url",
      "similarity": 1.0
    },
    {
      "story_id": "story_0dc626785ea2",
      "item_id": "afc5957ce3572a4faf97422848d004b64a4c7fd5",
      "merged_into": "story_0dc626785ea2",
      "reason": "canonical_url",
      "similarity": 1.0
    },
    {
      "story_id": "story_41cbd1bfdba4",
      "item_id": "64d6e483deaf4723251906f03754290354333448",
      "merged_into": "story_41cbd1bfdba4",
      "reason": "canonical_url",
      "similarity": 1.0
    },
    {
      "story_id": "story_cec3250340cd",
      "item_id": "27cf8d06a26505a7b8f0767f1efe31aabc650dc5",
      "merged_into": "story_cec3250340cd",
      "reason": "canonical_url",
      "similarity": 1.0
    },
    {
      "story_id": "story_d4213568f8bb",
      "item_id": "9a394173f23948a23c8336e8549e4539af2f2704",
      "merged_into": "story_d4213568f8bb",
      "reason": "canonical_url",
      "similarity": 1.0
    },
    {
      "story_id": "story_774f7412d1a3",
      "item_id": "c2c8537a7d27caf1e103b0647717e0c1932c2168",
      "merged_into": "story_774f7412d1a3",
      "reason": "canonical_url",
      "similarity": 1.0
    },
    {
      "story_id": "story_774f7412d1a3",
      "item_id": "3e4a63212f6b53f23c6b9bfb3557d2a5f01dcdf4",
      "merged_into": "story_774f7412d1a3",
      "reason": "canonical_url",
      "similarity": 1.0
    },
    {
      "story_id": "story_e2fca99e8fa5",
      "item_id": "98317fe6e0049b8208182ec3e52137983ba225fe",
      "merged_into": "story_e2fca99e8fa5",
      "reason": "canonical_url",
      "similarity": 1.0
    },
    {
      "story_id": "story_774f7412d1a3",
      "item_id": "471a43de3ca1c76305cd4c078c60801261a831ac",
      "merged_into": "story_774f7412d1a3",
      "reason": "canonical_url",
      "similarity": 1.0
    },
    {
      "story_id": "story_774f7412d1a3",
      "item_id": "7997d235a3c06506eb2f56fbbd4d17bee3c95275",
      "merged_into": "story_774f7412d1a3",
      "reason": "canonical_url",
      "similarity": 1.0
    },
    {
      "story_id": "story_774f7412d1a3",
      "item_id": "8e591550e16f4f8c113fe4adcf17a8205c322cc1",
      "merged_into": "story_774f7412d1a3",
      "reason": "canonical_url",
      "similarity": 1.0
    },
    {
      "story_id": "story_774f7412d1a3",
      "item_id": "631e5bc405e966ddd53bac3adccb1bc6eb7412dd",
      "merged_into": "story_774f7412d1a3",
      "reason": "canonical_url",
      "similarity": 1.0
    },
    {
      "story_id": "story_774f7412d1a3",
      "item_id": "e693ebc48b9a1771c032d075dd6b07b029b5405c",
      "merged_into": "story_774f7412d1a3",
      "reason": "canonical_url",
      "similarity": 1.0
    },
    {
      "story_id": "story_774f7412d1a3",
      "item_id": "15c3caccbef7f77d69c0d3d2e2828bb14cf2f0f6",
      "merged_into": "story_774f7412d1a3",
      "reason": "canonical_url",
      "similarity": 1.0
    }
  ]
}