{
  "generated_at": "2026-06-17T07:36:08.217749Z",
  "merge_strategy": "url_or_title_similarity_v0_6",
  "total_events": 11,
  "events": [
    {
      "story_id": "story_928be2f1d299",
      "item_id": "46bba61928aed9a2ee1bf68cac13aff1762faf6b",
      "merged_into": "story_928be2f1d299",
      "reason": "canonical_url",
      "similarity": 1.0
    },
    {
      "story_id": "story_774f7412d1a3",
      "item_id": "577859cccbd06148eae48936a8e7d649efdbe08e",
      "merged_into": "story_774f7412d1a3",
      "reason": "canonical_url",
      "similarity": 1.0
    },
    {
      "story_id": "story_774f7412d1a3",
      "item_id": "6e2771fe4af5fae1f94bc800dcd42610a2dc3fd0",
      "merged_into": "story_774f7412d1a3",
      "reason": "canonical_url",
      "similarity": 1.0
    },
    {
      "story_id": "story_774f7412d1a3",
      "item_id": "079475043ab744087d560e0715190de14c4d3f25",
      "merged_into": "story_774f7412d1a3",
      "reason": "canonical_url",
      "similarity": 1.0
    },
    {
      "story_id": "story_774f7412d1a3",
      "item_id": "3b4be744ff7c94f0ead969944a1942a5579c3668",
      "merged_into": "story_774f7412d1a3",
      "reason": "canonical_url",
      "similarity": 1.0
    },
    {
      "story_id": "story_774f7412d1a3",
      "item_id": "203748948121e9edb8ec36b80a8963728bf5a34f",
      "merged_into": "story_774f7412d1a3",
      "reason": "canonical_url",
      "similarity": 1.0
    },
    {
      "story_id": "story_774f7412d1a3",
      "item_id": "56b56ce1bea8e754c098b81151d9de3968c54ba5",
      "merged_into": "story_774f7412d1a3",
      "reason": "canonical_url",
      "similarity": 1.0
    },
    {
      "story_id": "story_774f7412d1a3",
      "item_id": "d7f666b2662bdbba6f5720151e6843ca4ec8ec76",
      "merged_into": "story_774f7412d1a3",
      "reason": "canonical_url",
      "similarity": 1.0
    },
    {
      "story_id": "story_774f7412d1a3",
      "item_id": "8aefdeff1a832ed4fdc81e85cfe1906512084020",
      "merged_into": "story_774f7412d1a3",
      "reason": "canonical_url",
      "similarity": 1.0
    },
    {
      "story_id": "story_774f7412d1a3",
      "item_id": "222ce6efa57c3633d2ad83b1ca2be7ec1c040843",
      "merged_into": "story_774f7412d1a3",
      "reason": "canonical_url",
      "similarity": 1.0
    },
    {
      "story_id": "story_774f7412d1a3",
      "item_id": "be408017e1eda620ed77b4cc0aed5d03f91d8d42",
      "merged_into": "story_774f7412d1a3",
      "reason": "canonical_url",
      "similarity": 1.0
    }
  ]
}